s1ncipher.py
s1ncipher-0.3.2.dist-info/licenses/LICENSE
s1ncipher-0.3.2.dist-info/METADATA
s1ncipher-0.3.2.dist-info/WHEEL
s1ncipher-0.3.2.dist-info/top_level.txt
s1ncipher-0.3.2.dist-info/RECORD
