Metadata-Version: 2.4
Name: s1ncipher
Version: 0.3.2
Summary: A simple cipher keeps original order and can be search partly by encode 1 byte data to many bytes.
Author: rRR0VrFP
Maintainer: rRR0VrFP
Keywords: cipherutils,s1ncipher
Classifier: Development Status :: 5 - Production/Stable
Classifier: Intended Audience :: Developers
Classifier: Topic :: Software Development :: Libraries :: Python Modules
Classifier: License :: OSI Approved :: MIT License
Classifier: Programming Language :: Python :: 3
Classifier: Programming Language :: Python :: 3 :: Only
License-File: LICENSE
Requires-Dist: zenutils
Dynamic: author
Dynamic: classifier
Dynamic: description
Dynamic: description-content-type
Dynamic: keywords
Dynamic: license-file
Dynamic: maintainer
Dynamic: requires-dist
Dynamic: summary
